LICENSE
README.md
setup.py
ca_imm_source.egg-info/PKG-INFO
ca_imm_source.egg-info/SOURCES.txt
ca_imm_source.egg-info/dependency_links.txt
ca_imm_source.egg-info/entry_points.txt
ca_imm_source.egg-info/requires.txt
ca_imm_source.egg-info/top_level.txt
source/__init__.py
source/datasource.py
source/excel.py
source/format.py
source/infosheet.py
source/style.py
source/tablesheet.py